pydeconz/__init__.py
pydeconz/__main__.py
pydeconz/config.py
pydeconz/errors.py
pydeconz/gateway.py
pydeconz/py.typed
pydeconz/utils.py
pydeconz/websocket.py
pydeconz/interfaces/__init__.py
pydeconz/interfaces/alarm_systems.py
pydeconz/interfaces/api_handlers.py
pydeconz/interfaces/events.py
pydeconz/interfaces/groups.py
pydeconz/interfaces/lights.py
pydeconz/interfaces/scenes.py
pydeconz/interfaces/sensors.py
pydeconz/models/__init__.py
pydeconz/models/alarm_system.py
pydeconz/models/api.py
pydeconz/models/deconz_device.py
pydeconz/models/event.py
pydeconz/models/group.py
pydeconz/models/scene.py
pydeconz/models/light/__init__.py
pydeconz/models/light/configuration_tool.py
pydeconz/models/light/cover.py
pydeconz/models/light/light.py
pydeconz/models/light/lock.py
pydeconz/models/light/range_extender.py
pydeconz/models/light/siren.py
pydeconz/models/sensor/__init__.py
pydeconz/models/sensor/air_purifier.py
pydeconz/models/sensor/air_quality.py
pydeconz/models/sensor/alarm.py
pydeconz/models/sensor/ancillary_control.py
pydeconz/models/sensor/battery.py
pydeconz/models/sensor/carbon_dioxide.py
pydeconz/models/sensor/carbon_monoxide.py
pydeconz/models/sensor/consumption.py
pydeconz/models/sensor/daylight.py
pydeconz/models/sensor/door_lock.py
pydeconz/models/sensor/fire.py
pydeconz/models/sensor/formaldehyde.py
pydeconz/models/sensor/generic_flag.py
pydeconz/models/sensor/generic_status.py
pydeconz/models/sensor/humidity.py
pydeconz/models/sensor/light_level.py
pydeconz/models/sensor/moisture.py
pydeconz/models/sensor/open_close.py
pydeconz/models/sensor/particulate_matter.py
pydeconz/models/sensor/power.py
pydeconz/models/sensor/presence.py
pydeconz/models/sensor/pressure.py
pydeconz/models/sensor/relative_rotary.py
pydeconz/models/sensor/switch.py
pydeconz/models/sensor/temperature.py
pydeconz/models/sensor/thermostat.py
pydeconz/models/sensor/time.py
pydeconz/models/sensor/vibration.py
pydeconz/models/sensor/water.py
pydeconz-119.dist-info/LICENSE
pydeconz-119.dist-info/METADATA
pydeconz-119.dist-info/WHEEL
pydeconz-119.dist-info/entry_points.txt
pydeconz-119.dist-info/top_level.txt
pydeconz-119.dist-info/RECORD
